rac_es/__init__.py
rac_es/analyzers.py
rac_es/documents.py
tests/__init__.py
tests/test_documents.py
rac_es-1.1.0.dist-info/LICENSE
rac_es-1.1.0.dist-info/METADATA
rac_es-1.1.0.dist-info/WHEEL
rac_es-1.1.0.dist-info/top_level.txt
rac_es-1.1.0.dist-info/RECORD
