Metadata-Version: 2.1
Name: rac_es
Version: 1.1.0
Summary: Helpers for Rockefeller Archive Center's Elasticsearch implementation.
Home-page: http://github.com/RockefellerArchiveCenter/rac_es
Author: Rockefeller Archive Center
Author-email: archive@rockarch.org
License: MIT
License-File: LICENSE
Requires-Dist: elasticsearch
Requires-Dist: elasticsearch-dsl
